MANIFEST.in
README.rst
setup.cfg
setup.py
django_mcmailer.egg-info/PKG-INFO
django_mcmailer.egg-info/SOURCES.txt
django_mcmailer.egg-info/dependency_links.txt
django_mcmailer.egg-info/requires.txt
django_mcmailer.egg-info/top_level.txt
mcmailer/__init__.py
mcmailer/admin.py
mcmailer/apps.py
mcmailer/forms.py
mcmailer/models.py
mcmailer/tests.py
mcmailer/urls.py
mcmailer/views.py
mcmailer/migrations/0001_initial.py
mcmailer/migrations/__init__.py
mcmailer/static/mcmailer/mcmailer_main.js
mcmailer/templates/auth_gmail_address.html
mcmailer/templates/no_index_base.html
mcmailer/templates/send_test_email.html
mcmailer/utils/date_utils.py
mcmailer/utils/sendgmail.py